netlify_builds/__init__.py
netlify_builds/cli.py
netlify_builds-1.4.0.dist-info/licenses/LICENSE
netlify_builds-1.4.0.dist-info/METADATA
netlify_builds-1.4.0.dist-info/WHEEL
netlify_builds-1.4.0.dist-info/entry_points.txt
netlify_builds-1.4.0.dist-info/top_level.txt
netlify_builds-1.4.0.dist-info/RECORD
