Metadata-Version: 2.4
Name: netlify-builds
Version: 1.4.0
Summary: A command line utility to check build usage across multiple Netlify accounts
Author-email: Bruno Alla <alla.brunoo@gmail.com>
License-Expression: MIT
Project-URL: Bug Tracker, https://github.com/browniebroke/netlify-builds/issues
Project-URL: Changelog, https://netlify-builds.readthedocs.io/changelog.html
Project-URL: Mastodon, https://fosstodon.org/@browniebroke
Project-URL: repository, https://github.com/browniebroke/netlify-builds
Project-URL: Twitter, https://twitter.com/_BrunoAlla
Classifier: Development Status :: 2 - Pre-Alpha
Classifier: Intended Audience :: Developers
Classifier: Natural Language :: English
Classifier: Operating System :: OS Independent
Classifier: Programming Language :: Python :: 3 :: Only
Classifier: Programming Language :: Python :: 3.10
Classifier: Programming Language :: Python :: 3.11
Classifier: Programming Language :: Python :: 3.12
Classifier: Programming Language :: Python :: 3.13
Classifier: Programming Language :: Python :: 3.14
Classifier: Topic :: Software Development :: Libraries
Requires-Python: >=3.10
License-File: LICENSE
Requires-Dist: httpx>=0.27.2
Requires-Dist: python-dateutil>=2.8
Requires-Dist: rich>=10
Dynamic: license-file
